Workbook

Sheet Vendor Invoice Data
A2: GST Vendor Invoice Data
A3: Sample purchase invoice data prepared for GST ITC Reconciliation and GSTR 2B comparison
A4: Vendor Name | B4: GSTIN | C4: Supplier State | D4: Place of Supply | E4: Invoice No. | F4: Invoice Date | G4: Taxable Value (Rs.) | H4: CGST (Rs.) | I4: SGST (Rs.) | J4: IGST (Rs.) | K4: Total GST (Rs.) | L4: ITC as per GSTR-2B (Rs.) | M4: ITC as per GSTR-3B (Rs.)
A5: =('GST ITC Reconciliation'!A5) -> Dhara Industries | B5: 19ABCDE1234G1Z5 | C5: West Bengal | D5: West Bengal | E5: INV/1001 | F5: 46117 | G5: 555556 | H5: =IF(C5=D5,G5*9%,0) -> 50000.04 | I5: =IF(C5=D5,G5*9%,0) -> 50000.04 | J5: =IF(C5<>D5,ROUND(G5*18%,0),0) -> 0 | K5: =SUM(H5:J5) -> 100000.08 | L5: =('GST ITC Reconciliation'!C5) -> 100000 | M5: =('GST ITC Reconciliation'!D5) -> 100000
A6: =('GST ITC Reconciliation'!A6) -> Novatal Automobile Pvt Ltd | B6: 19XYZLK6789G4Z5 | C6: West Bengal | D6: West Bengal | E6: INV/1002 | F6: 46120 | G6: 429444 | H6: =IF(C6=D6,G6*9%,0) -> 38649.96 | I6: =IF(C6=D6,G6*9%,0) -> 38649.96 | J6: =IF(C6<>D6,ROUND(G6*18%,0),0) -> 0 | K6: =SUM(H6:J6) -> 77299.92 | L6: =('GST ITC Reconciliation'!C6) -> 77300 | M6: =('GST ITC Reconciliation'!D6) -> 77300
A7: =('GST ITC Reconciliation'!A7) -> Agarwal Jewellers | B7: 24ABCFG5678L1Z2 | C7: Gujarat | D7: Gujarat | E7: INV/1003 | F7: 46122 | G7: 222778 | H7: =IF(C7=D7,G7*9%,0) -> 20050.02 | I7: =IF(C7=D7,G7*9%,0) -> 20050.02 | J7: =IF(C7<>D7,ROUND(G7*18%,0),0) -> 0 | K7: =SUM(H7:J7) -> 40100.04 | L7: =('GST ITC Reconciliation'!C7) -> 40100 | M7: =('GST ITC Reconciliation'!D7) -> 33100
A8: =('GST ITC Reconciliation'!A8) -> Amit & Sons Ltd | B8: 27PQRSX3456M1Z8 | C8: Gujarat | D8: Gujarat | E8: INV/1004 | F8: 46124 | G8: 188889 | H8: =IF(C8=D8,G8*9%,0) -> 17000.01 | I8: =IF(C8=D8,G8*9%,0) -> 17000.01 | J8: =IF(C8<>D8,ROUND(G8*18%,0),0) -> 0 | K8: =SUM(H8:J8) -> 34000.02 | L8: =('GST ITC Reconciliation'!C8) -> 34000 | M8: =('GST ITC Reconciliation'!D8) -> 34000
A9: =('GST ITC Reconciliation'!A9) -> Eastern Chemicals Pvt Ltd | B9: 19LMNOP9876Q1Z6 | C9: Maharashtra | D9: Maharashtra | E9: INV/1005 | F9: 46127 | G9: 419444 | H9: =IF(C9=D9,G9*9%,0) -> 37749.96 | I9: =IF(C9=D9,G9*9%,0) -> 37749.96 | J9: =IF(C9<>D9,ROUND(G9*18%,0),0) -> 0 | K9: =SUM(H9:J9) -> 75499.92 | L9: =('GST ITC Reconciliation'!C9) -> 75500 | M9: =('GST ITC Reconciliation'!D9) -> 0
A10: =('GST ITC Reconciliation'!A10) -> Das Manufacturers | B10: 19QWERT4567N1Z9 | C10: West Bengal | D10: West Bengal | E10: INV/1006 | F10: 46130 | G10: 95000 | H10: =IF(C10=D10,G10*9%,0) -> 8550 | I10: =IF(C10=D10,G10*9%,0) -> 8550 | J10: =IF(C10<>D10,ROUND(G10*18%,0),0) -> 0 | K10: =SUM(H10:J10) -> 17100 | L10: =('GST ITC Reconciliation'!C10) -> 17100 | M10: =('GST ITC Reconciliation'!D10) -> 17100
A11: =('GST ITC Reconciliation'!A11) -> Raj Electricals | B11: 19HJKLM2345R1Z4 | C11: West Bengal | D11: Odisha | E11: INV/1007 | F11: 46134 | G11: 238889 | H11: =IF(C11=D11,G11*9%,0) -> 0 | I11: =IF(C11=D11,G11*9%,0) -> 0 | J11: =IF(C11<>D11,ROUND(G11*18%,0),0) -> 43000 | K11: =SUM(H11:J11) -> 43000 | L11: =('GST ITC Reconciliation'!C11) -> 43000.02 | M11: =('GST ITC Reconciliation'!D11) -> 51300

Sheet GST ITC Reconciliation
A1: GST Input Tax Credit (ITC) Reconciliation
A2: Comparing ITC claimed in GSTR-3B against ITC available as per GSTR-2B, for a sample business (April 2026)
A4: Vendor Name | B4: Invoice No. | C4: ITC as per GSTR-2B (Rs.) | D4: ITC claimed in GSTR-3B (Rs.) | E4: Difference (Rs.) | F4: Remarks
A5: Dhara Industries | B5: INV/1001 | C5: 100000 | D5: 100000 | E5: =D5-C5 -> 0 | F5: =IF(E5=0,"Matched",IF(E5<0,"Under-claimed - follow up","Over-claimed - needs reversal")) -> Matched
A6: Novatal Automobile Pvt Ltd | B6: INV/1002 | C6: 77300 | D6: 77300 | E6: =D6-C6 -> 0 | F6: =IF(E6=0,"Matched",IF(E6<0,"Under-claimed - follow up","Over-claimed - needs reversal")) -> Matched
A7: Agarwal Jewellers | B7: INV/1003 | C7: 40100 | D7: 33100 | E7: =D7-C7 -> -7000 | F7: =IF(E7=0,"Matched",IF(E7<0,"Under-claimed - follow up","Over-claimed - needs reversal")) -> Under-claimed - follow up
A8: Amit & Sons Ltd | B8: INV/1004 | C8: 34000 | D8: 34000 | E8: =D8-C8 -> 0 | F8: =IF(E8=0,"Matched",IF(E8<0,"Under-claimed - follow up","Over-claimed - needs reversal")) -> Matched
A9: Eastern Chemicals Pvt Ltd | B9: INV/1005 | C9: 75500 | D9: 0 | E9: =D9-C9 -> -75500 | F9: =IF(E9=0,"Matched",IF(E9<0,"Under-claimed - follow up","Over-claimed - needs reversal")) -> Under-claimed - follow up
A10: Das Manufacturers | B10: INV/1006 | C10: 17100 | D10: 17100 | E10: =D10-C10 -> 0 | F10: =IF(E10=0,"Matched",IF(E10<0,"Under-claimed - follow up","Over-claimed - needs reversal")) -> Matched
A11: Raj Electricals | B11: INV/1007 | C11: 43000.02 | D11: 51300 | E11: =D11-C11 -> 8299.98 | F11: =IF(E11=0,"Matched",IF(E11<0,"Under-claimed - follow up","Over-claimed - needs reversal")) -> Over-claimed - needs reversal
A12: TOTAL | C12: =SUM(C5:C11) -> 387000.02 | D12: =SUM(D5:D11) -> 312800 | E12: =SUM(E5:E11) -> -74200.02
A14: What this shows:
A15: • GSTR-2B is the auto-generated statement showing ITC available to a business based on what its vendors have uploaded/filed.
A16: • GSTR-3B is the summary return where a business actually claims that ITC while paying its GST liability.
A17: • Ideally, the ITC claimed in GSTR-3B should match GSTR-2B. Any difference needs to be checked and corrected.
A18: • In this example: Raj Electricals shows Rs. 8,300 claimed in excess (needs to be reversed with interest), and Eastern Chemicals' ITC of Rs. 75,500 was missed entirely and should be claimed on or before 30 November following the end of the relevant Financial Year or the date of filing Annual Return for that Financial Year, whichever is earlier.
